{
  "project_info": {
    "project_number": "709801037206",
    "project_id": "zzoomchat",
    "storage_bucket": "zzoomchat.appspot.com"
  },
  "client": [
    {
      "client_info": {
        "mobilesdk_app_id": "1:709801037206:android:f08efbec37119b9c0061b7",
        "android_client_info": {
          "package_name": "com.example.flutter_application_1"
        }
      },
      "oauth_client": [
        {
          "client_id": "709801037206-v2vah6lv79afiudsdvbdg8r0nn0r5874.apps.googleusercontent.com",
          "client_type": 3
        }
      ],
      "api_key": [
        {
          "current_key": "AIzaSyBOqpDpt2q38Ckz2vQ30akg4fX0Ove1iTs"
        }
      ],
      "services": {
        "appinvite_service": {
          "other_platform_oauth_client": [
            {
              "client_id": "709801037206-v2vah6lv79afiudsdvbdg8r0nn0r5874.apps.googleusercontent.com",
              "client_type": 3
            }
          ]
        }
      }
    }
  ],
  "configuration_version": "1"
}